{
  "description": "多租户水果店小程序",
  "packOptions": {
    "ignore": [],
    "include": []
  },
  "setting": {
    "urlCheck": true,
    "es6": true,
    "enhance": true,
    "postcss": true,
    "preloadBackgroundData": false,
    "minified": true,
    "newFeature": true,
    "coverView": true,
    "nodeModules": false,
    "autoAudits": false,
    "showShadowRootInWxmlPanel": true,
    "uglifyFileName": true,
    "checkInvalidKey": true,
    "checkSiteMap": true,
    "uploadWithSourceMap": true,
    "compileHotReLoad": false,
    "lazyloadPlaceholderEnable": false,
    "useMultiFrameRuntime": true,
    "useApiHook": true,
    "useApiHostProcess": true,
    "babelSetting": {
      "ignore": [],
      "disablePlugins": [],
      "outputPath": ""
    },
    "enableEngineNative": false,
    "bundle": false,
    "useIsolateContext": true,
    "useCompilerModule": true,
    "userConfirmedUseCompilerModuleSwitch": false,
    "userConfirmedBundleSwitch": false
  },
  "compileType": "miniprogram",
  "libVersion": "2.14.1",
  "appid": "wx1234567890123456",
  "projectname": "merchant_platform",
  "debugOptions": {
    "hidedInDevtools": []
  },
  "isGameTourist": false,
  "cloudfunctionTemplateRoot": "cloudfunctions/"
}